PYGAME_GUI_EXT/__init__.py
PYGAME_GUI_EXT/src/Container.py
PYGAME_GUI_EXT/src/__init__.py
PYGAME_GUI_EXT/src/testing.py
PYGAME_GUI_EXT/src/Component/Elements.py
PYGAME_GUI_EXT/src/Component/__init__.py
PYGAME_GUI_EXT-0.0.2.dist-info/LICENSE
PYGAME_GUI_EXT-0.0.2.dist-info/METADATA
PYGAME_GUI_EXT-0.0.2.dist-info/WHEEL
PYGAME_GUI_EXT-0.0.2.dist-info/top_level.txt
PYGAME_GUI_EXT-0.0.2.dist-info/RECORD
