Metadata-Version: 2.1
Name: PYGAME-GUI-EXT
Version: 0.0.2
Summary: A gui extension for pygame
Home-page: https://github.com/Yousef-Div123/Pygame-UI
Author: YousefDiv
Author-email: yousefdiv123@outlook.com
License: MIT
Platform: UNKNOWN
Classifier: License :: OSI Approved :: MIT License
Classifier: Programming Language :: Python :: 3
Classifier: Operating System :: OS Independent
Requires-Python: >=3
License-File: LICENSE
Requires-Dist: pygame>=2.1.2
Provides-Extra: dev
Requires-Dist: twine>=4.0.2; extra == "dev"
